dex_aggregator/__init__.py
dex_aggregator/config/__init__.py
dex_aggregator/config/contracts.py
dex_aggregator/config/settings.py
dex_aggregator/core/__init__.py
dex_aggregator/core/exceptions.py
dex_aggregator/core/factory.py
dex_aggregator/core/interfaces.py
dex_aggregator/core/abis/erc20.json
dex_aggregator/providers/__init__.py
dex_aggregator/providers/jupiter/__init__.py
dex_aggregator/providers/jupiter/client.py
dex_aggregator/providers/jupiter/constants.py
dex_aggregator/providers/jupiter/provider.py
dex_aggregator/providers/okx/__init__.py
dex_aggregator/providers/okx/client.py
dex_aggregator/providers/okx/provider.py
dex_aggregator/providers/okx/solana_provider.py
dex_aggregator/providers/raydium/__init__.py
dex_aggregator/providers/raydium/client.py
dex_aggregator/providers/raydium/constants.py
dex_aggregator/providers/raydium/provider.py
dex_aggregator/utils/__init__.py
dex_aggregator/utils/abi_helper.py
dex_aggregator/utils/logger.py
dex_aggregator/utils/web3_helper.py
dex_aggregator-0.7.0.dist-info/licenses/LICENSE
dex_aggregator-0.7.0.dist-info/METADATA
dex_aggregator-0.7.0.dist-info/WHEEL
dex_aggregator-0.7.0.dist-info/top_level.txt
dex_aggregator-0.7.0.dist-info/RECORD
